runkit/__init__.py
runkit-0.0.1a0.dist-info/AUTHORS.txt
runkit-0.0.1a0.dist-info/LICENSE.txt
runkit-0.0.1a0.dist-info/METADATA
runkit-0.0.1a0.dist-info/WHEEL
runkit-0.0.1a0.dist-info/top_level.txt
runkit-0.0.1a0.dist-info/zip-safe
runkit-0.0.1a0.dist-info/RECORD
