Metadata-Version: 2.1
Name: runkit
Version: 0.0.1a0
Summary: Provides utilities for command-line tools.
Home-page: https://github.com/high-dimensional/runkit
Author: High Dimensional Neurology Group, UCL
Author-email: pypi@highdimensional.net
License: BSD-3-Clause
Platform: any
Classifier: Framework :: Django
Classifier: Framework :: Wagtail
Classifier: Programming Language :: Python :: 3
Classifier: Programming Language :: Python :: 3.7
Classifier: License :: OSI Approved :: BSD License
Classifier: Operating System :: OS Independent
Requires-Python: >=3.7
License-File: LICENSE.txt
License-File: AUTHORS.txt
